Metadata-Version: 2.1
Name: pyrogram-aiopg-storage
Version: 0.3
Summary: aiopg storage for pyrogram
Home-page: https://github.com/parikls/pyrogram-aiopg-storage
Author: Dmytro Smyk
Author-email: porovozls@gmail.com
License: UNKNOWN
Platform: UNKNOWN
Classifier: Operating System :: OS Independent
Classifier: Intended Audience :: Developers
Classifier: Programming Language :: Python
Classifier: Programming Language :: Python :: 3.6
Classifier: Programming Language :: Python :: 3.7
Classifier: Programming Language :: Python :: 3.8
Classifier: Programming Language :: Python :: 3.9
Classifier: Programming Language :: Python :: 3.10
Requires-Python: >=3.6.0
